MANIFEST.in
README.rst
setup.py
archelonc/__init__.py
archelonc/command.py
archelonc/data.py
archelonc/search.py
archelonc.egg-info/PKG-INFO
archelonc.egg-info/SOURCES.txt
archelonc.egg-info/dependency_links.txt
archelonc.egg-info/entry_points.txt
archelonc.egg-info/requires.txt
archelonc.egg-info/top_level.txt
archelonc.egg-info/zip-safe
archelonc/tests/__init__.py
archelonc/tests/base.py
archelonc/tests/test_command.py
archelonc/tests/test_data.py
archelonc/tests/test_search.py
scripts/archelon