Metadata-Version: 1.1
Name: archelonc
Version: 0.6.0
Summary: Client connected to archelonc for Web shell history
Home-page: http://github.com/carsongee/archelon
Author: Carson Gee
Author-email: x@carsongee.com
License: AGPLv3
Platform: UNKNOWN
Classifier: Development Status :: 2 - Pre-Alpha
Classifier: Intended Audience :: Information Technology
Classifier: License :: OSI Approved :: GNU Affero General Public License v3
Classifier: Operating System :: POSIX :: Linux
Classifier: Programming Language :: Python :: 2.7
Classifier: Programming Language :: Python :: 3.3
Classifier: Programming Language :: Python :: 3.4
